spyrael/__init__.py
spyrael/encode.py
spyrael/poster.py
spyrael/streaminghttp.py
spyrael/utils.py
spyrael-0.0.1.dist-info/METADATA
spyrael-0.0.1.dist-info/WHEEL
spyrael-0.0.1.dist-info/top_level.txt
spyrael-0.0.1.dist-info/RECORD
